LICENSE
MANIFEST.in
README.md
pyproject.toml
setup.cfg
setup.py
completion/_kyoto
src/kyoto_reader/VERSION
src/kyoto_reader/__init__.py
src/kyoto_reader/base_phrase.py
src/kyoto_reader/cli.py
src/kyoto_reader/constants.py
src/kyoto_reader/coreference.py
src/kyoto_reader/document.py
src/kyoto_reader/ne.py
src/kyoto_reader/pas.py
src/kyoto_reader/reader.py
src/kyoto_reader/sentence.py
src/kyoto_reader.egg-info/PKG-INFO
src/kyoto_reader.egg-info/SOURCES.txt
src/kyoto_reader.egg-info/dependency_links.txt
src/kyoto_reader.egg-info/entry_points.txt
src/kyoto_reader.egg-info/not-zip-safe
src/kyoto_reader.egg-info/requires.txt
src/kyoto_reader.egg-info/top_level.txt
src/kyoto_reader/scripts/add_sems.py
src/kyoto_reader/scripts/docsplit.py
src/kyoto_reader/scripts/sexp.py
src/kyoto_reader/scripts/template.mk
tests/__init__.py
tests/conftest.py
tests/test_document.py
tests/test_jumandic.py
tests/test_reader.py
tests/data/compress_knp/knp.tar.gz
tests/data/compress_knp/knp.zip
tests/data/gzip_knp/w201106-0000060050.knp.gz
tests/data/gzip_knp/w201106-0000060560.knp.gz
tests/data/gzip_knp/w201106-0000060877.knp.gz
tests/data/gzip_knp/w201106-0000074273.knp.gz
tests/data/gzip_knp/w201106-0002000016.knp.gz
tests/data/gzip_knp/w201106-0002000028.knp.gz
tests/data/jumandic/0.json
tests/data/jumandic/1.json
tests/data/jumandic/2.json
tests/data/jumandic/3.json
tests/data/jumandic/4.json
tests/data/jumandic/5.json
tests/data/jumandic/test.dic
tests/data/knp/w201106-0000060050.knp
tests/data/knp/w201106-0000060560.knp
tests/data/knp/w201106-0000060877.knp
tests/data/knp/w201106-0000074273.knp
tests/data/knp/w201106-0002000016.knp
tests/data/knp/w201106-0002000028.knp