Metadata-Version: 2.1
Name: kyoto-reader
Version: 2.5.1
Summary: A KWDLC and KyotoCorpus parser
Home-page: https://github.com/ku-nlp/kyoto-reader
Author: Kurohashi-Kawahara Lab, Kyoto University
Author-email: contact@nlp.ist.i.kyoto-u.ac.jp
License: MIT
Keywords: NLP,KWDLC,KyotoCorpus,parser
Platform: UNKNOWN
Classifier: License :: OSI Approved :: MIT License
Classifier: Programming Language :: Python :: 3
Classifier: Programming Language :: Python :: 3.7
Classifier: Programming Language :: Python :: 3.8
Classifier: Programming Language :: Python :: 3.9
Classifier: Programming Language :: Python :: 3.10
Requires-Python: !=3.7.0,!=3.7.1,>=3.7
Provides-Extra: testing
License-File: LICENSE
